README.rst
setup.py
seamus/__init__.py
seamus/decorator.py
seamus/exceptions.py
seamus/seamus.py
seamus.egg-info/PKG-INFO
seamus.egg-info/SOURCES.txt
seamus.egg-info/dependency_links.txt
seamus.egg-info/top_level.txt