Metadata-Version: 1.0
Name: seamus
Version: 0.0.1
Summary: Makes testing refactored code easy
Home-page: https://github.com/nerandell/seamus
Author: Ankit Chandawala
Author-email: ankitchandawala@gmail.com
License: UNKNOWN
Platform: UNKNOWN
